Workbook

Sheet Menu
B2: Controle de Imposto de Renda
B3: ="Ano-calendário "&AnoBase&" | organize seus dados em um só lugar" -> Ano-calendário 2025 | organize seus dados em um só lugar
B5: NAVEGAÇÃO
B6: =HYPERLINK("#'Resumo'!A1","► Resumo") -> ► Resumo | C6: Totais, deduções e imposto estimado
B7: =HYPERLINK("#'Rendimentos'!A1","► Rendimentos") -> ► Rendimentos | C7: Salários, aluguéis, aplicações e isentos
B8: =HYPERLINK("#'Despesas'!A1","► Despesas") -> ► Despesas | C8: Saúde, educação, previdência, pensão
B9: =HYPERLINK("#'Bens_Direitos'!A1","► Bens e Direitos") -> ► Bens e Direitos | C9: Veículos, imóveis, investimentos
B10: =HYPERLINK("#'Dividas'!A1","► Dívidas") -> ► Dívidas | C10: Financiamentos e empréstimos
B11: =HYPERLINK("#'Dependentes'!A1","► Dependentes") -> ► Dependentes | C11: Cadastro e dedução por dependente
B12: =HYPERLINK("#'Checklist'!A1","► Checklist") -> ► Checklist | C12: Documentos pendentes e concluídos
B13: =HYPERLINK("#'Config'!A1","► Configurações") -> ► Configurações | C13: Ano-base, limites, tabela e listas
B15: LINKS RÁPIDOS (Receita Federal e governo)
B16: =HYPERLINK("https://www.gov.br/receitafederal/pt-br/assuntos/meu-imposto-de-renda","↗ Meu Imposto de Renda") -> ↗ Meu Imposto de Renda | C16: Programa, regras e perguntas frequentes
B17: =HYPERLINK("https://cav.receita.fazenda.gov.br","↗ Portal e-CAC") -> ↗ Portal e-CAC | C17: Declaração pré-preenchida, extratos e pendências
B18: =HYPERLINK("https://servicos.receita.fazenda.gov.br/servicos/cpf/consultasituacao/consultapublica.asp","↗ Consulta de CPF") -> ↗ Consulta de CPF | C18: Situação cadastral do CPF
B19: =HYPERLINK("https://meu.inss.gov.br","↗ Meu INSS") -> ↗ Meu INSS | C19: Informe de rendimentos de aposentadoria/pensão
B20: =HYPERLINK("https://www.gov.br/receitafederal/pt-br","↗ Receita Federal") -> ↗ Receita Federal | C20: Site oficial
B22: COMO USAR
B23: 1) Confira o ano-calendário e os limites na aba Config (células amarelas).
B24: 2) Cadastre rendimentos, despesas, bens, dívidas e dependentes nas colunas azuis.
B25: 3) Listas suspensas e validações bloqueiam datas, valores e documentos inválidos.
B26: 4) Linhas em laranja indicam dados incompletos; acompanhe os alertas no Resumo.
B27: 5) As linhas 5 das abas de cadastro são EXEMPLOS: apague-as antes de usar.
B29: Legenda: azul = entrada manual | preto = fórmula | cinza = coluna automática | amarelo = parâmetro-chave

Sheet Resumo
A1: =HYPERLINK("#'Menu'!A1","◄ Voltar ao Menu") -> ◄ Voltar ao Menu
A2: Resumo da declaração (estimativa)
A3: ="Ano-calendário: "&AnoBase -> Ano-calendário: 2025
A5: RENDIMENTOS
A6: Rendimentos tributáveis | B6: =SUMIFS(Rendimentos!$E$5:$E$204,Rendimentos!$G$5:$G$204,"Tributável") -> 8500
A7: Rendimentos isentos | B7: =SUMIFS(Rendimentos!$E$5:$E$204,Rendimentos!$G$5:$G$204,"Isento") -> 0
A8: Tributação exclusiva/definitiva | B8: =SUMIFS(Rendimentos!$E$5:$E$204,Rendimentos!$G$5:$G$204,"Exclusiva/definitiva") -> 0
A9: Imposto retido na fonte (total) | B9: =SUM(Rendimentos!$F$5:$F$204) -> 950.4
A11: DEDUÇÕES
A12: Previdência oficial (INSS) | B12: =SUMIFS(Despesas!$G$5:$G$204,Despesas!$D$5:$D$204,"Previdência oficial (INSS)") -> 0
A13: PGBL (limitado a % da renda tributável) | B13: =MIN(SUMIFS(Despesas!$G$5:$G$204,Despesas!$D$5:$D$204,"PGBL"),LimPGBL*B6) -> 0
A14: Pensão alimentícia | B14: =SUMIFS(Despesas!$G$5:$G$204,Despesas!$D$5:$D$204,"Pensão alimentícia") -> 0
A15: Saúde (sem limite) | B15: =SUMIFS(Despesas!$G$5:$G$204,Despesas!$D$5:$D$204,"Saúde") -> 420
A16: Educação (limitada por pessoa) | B16: =MIN(SUMIFS(Despesas!$G$5:$G$204,Despesas!$D$5:$D$204,"Educação"),LimEduc*(1+B18)) -> 0 | C16: Limite aplicado ao titular + dependentes (simplificação)
A17: Dedução de dependentes | B17: =B18*DedDep -> 2275.08
A18: Quantidade de dependentes | B18: =COUNTA(Dependentes!$A$5:$A$60) -> 1
A19: Total de deduções | B19: =B12+B13+B14+B15+B16+B17 -> 2695.08
A21: CÁLCULO ESTIMADO
A22: Base de cálculo | B22: =MAX(0,B6-B19) -> 5804.92
A23: Imposto devido (tabela progressiva) | B23: =MAX(0,B22*INDEX(Config!$B$24:$B$28,MATCH(B22,Config!$A$24:$A$28,1))-INDEX(Config!$C$24:$C$28,MATCH(B22,Config!$A$24:$A$28,1))) -> 0
A24: Imposto retido na fonte | B24: =B9 -> 950.4
A25: Saldo: positivo = a pagar | negativo = a restituir | B25: =B23-B24 -> -950.4
A27: PATRIMÔNIO
A28: Bens e direitos em 31/12 (ano anterior) | B28: =SUM(Bens_Direitos!$C$5:$C$204) -> 42000
A29: Bens e direitos em 31/12 (ano-calendário) | B29: =SUM(Bens_Direitos!$D$5:$D$204) -> 40000
A30: Dívidas em 31/12 (ano-calendário) | B30: =SUM(Dividas!$D$5:$D$204) -> 9000
A31: Patrimônio líquido (ano-calendário) | B31: =B29-B30 -> 31000
A32: Evolução patrimonial (bens) | B32: =B29-B28 -> -2000
A34: CONTROLE
A35: Documentos concluídos (checklist) | B35: =IFERROR(COUNTIF(Checklist!$C$5:$C$23,"Concluído")/COUNTA(Checklist!$A$5:$A$23),0) -> 0
A36: Alerta: rendimentos sem CPF/CNPJ ou tipo | B36: =SUMPRODUCT((Rendimentos!$E$5:$E$204<>"")*((Rendimentos!$C$5:$C$204="")+(Rendimentos!$D$5:$D$204="")>0)) -> 0
A37: Alerta: despesas sem CPF/CNPJ ou categoria | B37: =SUMPRODUCT((Despesas!$E$5:$E$204<>"")*((Despesas!$C$5:$C$204="")+(Despesas!$D$5:$D$204="")>0)) -> 0
A39: Estimativa para organização dos dados. Confira sempre os valores e regras no programa oficial da Receita Federal.

Sheet Rendimentos
A1: =HYPERLINK("#'Menu'!A1","◄ Voltar ao Menu") -> ◄ Voltar ao Menu
A2: Rendimentos recebidos no ano
A3: Preencha as colunas em azul. Colunas cinzas são automáticas. A linha 5 é um EXEMPLO: substitua ou apague.
A4: Data | B4: Fonte pagadora | C4: CPF/CNPJ (só números) | D4: Tipo de rendimento | E4: Valor bruto (R$) | F4: IR retido (R$) | G4: Classificação (auto) | H4: Mês (auto) | I4: Comprovante (link/arquivo) | J4: Observações
A5: 45721 | B5: Empresa Exemplo Ltda | C5: 12345678000190 | D5: Salário / trabalho assalariado | E5: 8500 | F5: 950.4 | G5: =IF(D5="","",IFERROR(INDEX(Config!$B$10:$B$19,MATCH(D5,Config!$A$10:$A$19,0)),"")) -> Tributável | H5: =IF(A5="","",MONTH(A5)) -> 3 | J5: EXEMPLO - apague esta linha
G6: =IF(D6="","",IFERROR(INDEX(Config!$B$10:$B$19,MATCH(D6,Config!$A$10:$A$19,0)),"")) | H6: =IF(A6="","",MONTH(A6))
G7: =IF(D7="","",IFERROR(INDEX(Config!$B$10:$B$19,MATCH(D7,Config!$A$10:$A$19,0)),"")) | H7: =IF(A7="","",MONTH(A7))
G8: =IF(D8="","",IFERROR(INDEX(Config!$B$10:$B$19,MATCH(D8,Config!$A$10:$A$19,0)),"")) | H8: =IF(A8="","",MONTH(A8))
G9: =IF(D9="","",IFERROR(INDEX(Config!$B$10:$B$19,MATCH(D9,Config!$A$10:$A$19,0)),"")) | H9: =IF(A9="","",MONTH(A9))
G10: =IF(D10="","",IFERROR(INDEX(Config!$B$10:$B$19,MATCH(D10,Config!$A$10:$A$19,0)),"")) | H10: =IF(A10="","",MONTH(A10))
G11: =IF(D11="","",IFERROR(INDEX(Config!$B$10:$B$19,MATCH(D11,Config!$A$10:$A$19,0)),"")) | H11: =IF(A11="","",MONTH(A11))
G12: =IF(D12="","",IFERROR(INDEX(Config!$B$10:$B$19,MATCH(D12,Config!$A$10:$A$19,0)),"")) | H12: =IF(A12="","",MONTH(A12))
G13: =IF(D13="","",IFERROR(INDEX(Config!$B$10:$B$19,MATCH(D13,Config!$A$10:$A$19,0)),"")) | H13: =IF(A13="","",MONTH(A13))
G14: =IF(D14="","",IFERROR(INDEX(Config!$B$10:$B$19,MATCH(D14,Config!$A$10:$A$19,0)),"")) | H14: =IF(A14="","",MONTH(A14))
G15: =IF(D15="","",IFERROR(INDEX(Config!$B$10:$B$19,MATCH(D15,Config!$A$10:$A$19,0)),"")) | H15: =IF(A15="","",MONTH(A15))
G16: =IF(D16="","",IFERROR(INDEX(Config!$B$10:$B$19,MATCH(D16,Config!$A$10:$A$19,0)),"")) | H16: =IF(A16="","",MONTH(A16))
G17: =IF(D17="","",IFERROR(INDEX(Config!$B$10:$B$19,MATCH(D17,Config!$A$10:$A$19,0)),"")) | H17: =IF(A17="","",MONTH(A17))
... G204: =IF(D204="","",IFERROR(INDEX(Config!$B$10:$B$19,MATCH(D204,Config!$A$10:$A$19,0)),"")) | H204: =IF(A204="","",MONTH(A204))

Sheet Despesas
A1: =HYPERLINK("#'Menu'!A1","◄ Voltar ao Menu") -> ◄ Voltar ao Menu
A2: Despesas dedutíveis
A3: Preencha as colunas em azul. Limites legais são aplicados na aba Resumo. A linha 5 é um EXEMPLO.
A4: Data | B4: Prestador / beneficiário | C4: CPF/CNPJ (só números) | D4: Categoria | E4: Valor pago (R$) | F4: Reembolsado (R$) | G4: Valor dedutível (auto) | H4: Comprovante (link/arquivo) | I4: Observações
A5: 45818 | B5: Clínica Exemplo | C5: 98765432000110 | D5: Saúde | E5: 420 | F5: 0 | G5: =IF(E5="","",MAX(0,E5-N(F5))) -> 420 | I5: EXEMPLO - apague esta linha
G6: =IF(E6="","",MAX(0,E6-N(F6)))
G7: =IF(E7="","",MAX(0,E7-N(F7)))
G8: =IF(E8="","",MAX(0,E8-N(F8)))
G9: =IF(E9="","",MAX(0,E9-N(F9)))
G10: =IF(E10="","",MAX(0,E10-N(F10)))
G11: =IF(E11="","",MAX(0,E11-N(F11)))
G12: =IF(E12="","",MAX(0,E12-N(F12)))
G13: =IF(E13="","",MAX(0,E13-N(F13)))
G14: =IF(E14="","",MAX(0,E14-N(F14)))
G15: =IF(E15="","",MAX(0,E15-N(F15)))
G16: =IF(E16="","",MAX(0,E16-N(F16)))
G17: =IF(E17="","",MAX(0,E17-N(F17)))
... G204: =IF(E204="","",MAX(0,E204-N(F204)))

Sheet Bens_Direitos
A1: =HYPERLINK("#'Menu'!A1","◄ Voltar ao Menu") -> ◄ Voltar ao Menu
A2: Bens e direitos
A3: Valores em reais. A linha 5 é um EXEMPLO: substitua ou apague.
A4: Grupo / tipo do bem | B4: Discriminação | C4: Situação em 31/12 do ano anterior (R$) | D4: Situação em 31/12 do ano-calendário (R$) | E4: Variação (auto) | F4: Observações
A5: Veículo automotor | B5: Carro de passeio (modelo/ano, placa) | C5: 42000 | D5: 40000 | E5: =IF(AND(C5="",D5=""),"",N(D5)-N(C5)) -> -2000 | F5: EXEMPLO - apague esta linha
E6: =IF(AND(C6="",D6=""),"",N(D6)-N(C6))
E7: =IF(AND(C7="",D7=""),"",N(D7)-N(C7))
E8: =IF(AND(C8="",D8=""),"",N(D8)-N(C8))
E9: =IF(AND(C9="",D9=""),"",N(D9)-N(C9))
E10: =IF(AND(C10="",D10=""),"",N(D10)-N(C10))
E11: =IF(AND(C11="",D11=""),"",N(D11)-N(C11))
E12: =IF(AND(C12="",D12=""),"",N(D12)-N(C12))
E13: =IF(AND(C13="",D13=""),"",N(D13)-N(C13))
E14: =IF(AND(C14="",D14=""),"",N(D14)-N(C14))
E15: =IF(AND(C15="",D15=""),"",N(D15)-N(C15))
E16: =IF(AND(C16="",D16=""),"",N(D16)-N(C16))
E17: =IF(AND(C17="",D17=""),"",N(D17)-N(C17))
... E204: =IF(AND(C204="",D204=""),"",N(D204)-N(C204))

Sheet Dividas
A1: =HYPERLINK("#'Menu'!A1","◄ Voltar ao Menu") -> ◄ Voltar ao Menu
A2: Dívidas e ônus reais
A3: Financiamentos, empréstimos etc. A linha 5 é um EXEMPLO.
A4: Credor | B4: Descrição da dívida | C4: Situação em 31/12 do ano anterior (R$) | D4: Situação em 31/12 do ano-calendário (R$) | E4: Variação (auto) | F4: Observações
A5: Banco Exemplo | B5: Financiamento do veículo | C5: 15000 | D5: 9000 | E5: =IF(AND(C5="",D5=""),"",N(D5)-N(C5)) -> -6000 | F5: EXEMPLO - apague esta linha
E6: =IF(AND(C6="",D6=""),"",N(D6)-N(C6))
E7: =IF(AND(C7="",D7=""),"",N(D7)-N(C7))
E8: =IF(AND(C8="",D8=""),"",N(D8)-N(C8))
E9: =IF(AND(C9="",D9=""),"",N(D9)-N(C9))
E10: =IF(AND(C10="",D10=""),"",N(D10)-N(C10))
E11: =IF(AND(C11="",D11=""),"",N(D11)-N(C11))
E12: =IF(AND(C12="",D12=""),"",N(D12)-N(C12))
E13: =IF(AND(C13="",D13=""),"",N(D13)-N(C13))
E14: =IF(AND(C14="",D14=""),"",N(D14)-N(C14))
E15: =IF(AND(C15="",D15=""),"",N(D15)-N(C15))
E16: =IF(AND(C16="",D16=""),"",N(D16)-N(C16))
E17: =IF(AND(C17="",D17=""),"",N(D17)-N(C17))
... E204: =IF(AND(C204="",D204=""),"",N(D204)-N(C204))

Sheet Dependentes
A1: =HYPERLINK("#'Menu'!A1","◄ Voltar ao Menu") -> ◄ Voltar ao Menu
A2: Dependentes
A3: Cada dependente gera dedução na aba Resumo. A linha 5 é um EXEMPLO: substitua ou apague.
A4: Nome | B4: CPF (só números) | C4: Parentesco | D4: Data de nascimento | E4: Idade em 31/12 (auto) | F4: Observações
A5: Filho Exemplo | B5: 11122233344 | C5: Filho(a) | D5: 42106 | E5: =IF(D5="","",DATEDIF(D5,DATE(AnoBase,12,31),"Y")) -> 10 | F5: EXEMPLO - apague esta linha
E6: =IF(D6="","",DATEDIF(D6,DATE(AnoBase,12,31),"Y"))
E7: =IF(D7="","",DATEDIF(D7,DATE(AnoBase,12,31),"Y"))
E8: =IF(D8="","",DATEDIF(D8,DATE(AnoBase,12,31),"Y"))
E9: =IF(D9="","",DATEDIF(D9,DATE(AnoBase,12,31),"Y"))
E10: =IF(D10="","",DATEDIF(D10,DATE(AnoBase,12,31),"Y"))
E11: =IF(D11="","",DATEDIF(D11,DATE(AnoBase,12,31),"Y"))
E12: =IF(D12="","",DATEDIF(D12,DATE(AnoBase,12,31),"Y"))
E13: =IF(D13="","",DATEDIF(D13,DATE(AnoBase,12,31),"Y"))
E14: =IF(D14="","",DATEDIF(D14,DATE(AnoBase,12,31),"Y"))
E15: =IF(D15="","",DATEDIF(D15,DATE(AnoBase,12,31),"Y"))
E16: =IF(D16="","",DATEDIF(D16,DATE(AnoBase,12,31),"Y"))
E17: =IF(D17="","",DATEDIF(D17,DATE(AnoBase,12,31),"Y"))
... E60: =IF(D60="","",DATEDIF(D60,DATE(AnoBase,12,31),"Y"))

Sheet Checklist
A1: =HYPERLINK("#'Menu'!A1","◄ Voltar ao Menu") -> ◄ Voltar ao Menu
A2: Checklist de documentos
A3: Atualize o status; o percentual concluído aparece no Resumo.
A4: Documento | B4: Onde obter | C4: Status | D4: Link de acesso
A5: Informe de rendimentos (empresa / INSS) | B5: RH da empresa ou Meu INSS | C5: Pendente | D5: =HYPERLINK("https://meu.inss.gov.br","Abrir ►") -> Abrir ►
A6: Informe de rendimentos dos bancos e corretoras | B6: Aplicativo ou internet banking do banco | C6: Pendente | D6: =HYPERLINK("https://www.gov.br/receitafederal/pt-br","Abrir ►") -> Abrir ►
A7: Recibos de despesas médicas | B7: Prestadores de saúde / plano de saúde | C7: Pendente
A8: Comprovantes de despesas com educação | B8: Escola / faculdade | C8: Pendente
A9: Informe de previdência privada (PGBL) | B9: Seguradora ou banco | C9: Pendente
A10: Extrato de bens e direitos (veículos, imóveis) | B10: Documentos do bem | C10: Pendente
A11: Saldo de dívidas e financiamentos em 31/12 | B11: Banco / financeira | C11: Pendente
A12: Declaração anterior (recibo) | B12: Meu Imposto de Renda (e-CAC) | C12: Pendente | D12: =HYPERLINK("https://www.gov.br/receitafederal/pt-br/assuntos/meu-imposto-de-renda","Abrir ►") -> Abrir ►
A13: Documentos dos dependentes (CPF, nascimento) | B13: Documentos pessoais | C13: Pendente

Sheet Config
A1: =HYPERLINK("#'Menu'!A1","◄ Voltar ao Menu") -> ◄ Voltar ao Menu
A2: Configurações e listas (base das validações)
A3: Ano-calendário | B3: 2025 | C3: Fonte: valores informados pelo autor do projeto com base na Receita Federal; CONFIRME os valores do ano em gov.br/receitafederal antes de declarar.
A4: Limite anual de educação (por pessoa) | B4: 3561.5
A5: Dedução anual por dependente | B5: 2275.08
A6: Limite PGBL (% da renda tributável) | B6: 0.12
A9: Tipo de rendimento | B9: Classificação | D9: Categoria de despesa | F9: Parentesco | H9: Status
A10: Salário / trabalho assalariado | B10: Tributável | D10: Saúde | F10: Cônjuge/companheiro(a) | H10: Pendente
A11: Aposentadoria / pensão | B11: Tributável | D11: Educação | F11: Filho(a) | H11: Em andamento
A12: Aluguel recebido de pessoa física | B12: Tributável | D12: Previdência oficial (INSS) | F12: Pai/mãe | H12: Concluído
A13: Trabalho autônomo | B13: Tributável | D13: PGBL | F13: Enteado(a)
A14: 13º salário | B14: Exclusiva/definitiva | D14: Pensão alimentícia | F14: Menor sob guarda
A15: PLR | B15: Exclusiva/definitiva | F15: Outro
A16: Aplicações financeiras (CDB, renda fixa) | B16: Exclusiva/definitiva
A17: Poupança / LCI / LCA | B17: Isento
A18: Lucros e dividendos | B18: Isento
A19: FGTS / indenizações | B19: Isento
A22: Tabela progressiva anual do IRPF (parâmetros editáveis - simplificada, 12 x tabela mensal)
A23: Limite inferior (R$/ano) | B23: Alíquota | C23: Parcela a deduzir (R$)
A24: 0 | B24: 0 | C24: 0
A25: 29145.6 | B25: 0.075 | C25: 2185.92
A26: 33919.8 | B26: 0.15 | C26: 4729.92
A27: 45012.6 | B27: 0.225 | C27: 8105.88
A28: 55976.16 | B28: 0.275 | C28: 10904.76
A30: As regras do IR mudam todo ano (inclusive a tabela e as isenções). Atualize as células em azul/amarelo antes de usar; a planilha é uma ESTIMATIVA e não substitui o programa da Receita.
